__init__.py
onepassword2.py
onepassword2-1.7.dist-info/METADATA
onepassword2-1.7.dist-info/WHEEL
onepassword2-1.7.dist-info/entry_points.txt
onepassword2-1.7.dist-info/top_level.txt
onepassword2-1.7.dist-info/RECORD
