Metadata-Version: 2.1
Name: onepassword2
Version: 1.7
Summary: A python wrapper for onepassword cli version 2
Home-page: https://github.com/krezreb/onepassword2
Author: krezreb
Author-email: josephbeeson@gmail.com
License: MIT
Platform: UNKNOWN
Requires-Dist: fuzzywuzzy
Requires-Dist: python-Levenshtein
